Workbook

Sheet Assumptions 
B3: Project Specifications | F3: Revenue | J3: Financing
J4: Financing | K4: YES
B5: Project Size DC kw | C5: 1650 | F5: PPA rate ($/kwh) | G5: 0.11 | J5: Debt % | K5: 0.8
B6: Project Size AC kw | C6: =C5/1.25 -> 1320 | F6: PPA escalator (%) | G6: 0.02 | J6: Debt | K6: =C21*K5-(K20*K18) -> 1830088.8
B7: Yield kwh/kwp | C7: 1150 | F7: PPA length (yr) | G7: 25 | J7: Term | K7: 20
B8: 1st year kwh | C8: =C7*C5 -> 1897500 | F8: tail rate assumption ($/kwh) | G8: 0.08 | J8: Rate % | K8: 0.055
B9: Degredation Assumption % | C9: 0.5 | J9: Fee % | K9: 0.005
B10: availability Assumption % | C10: 0.5 | J10: Transaction Fees | K10: =K9*K6 -> 9150.4441
B11: Projected useful life | C11: 25 | J11: DSCR target | K11: 1.2
B13: Project Costs | F13: Operating Costs | J13: Equity | K13: =C23-K6-(K20*K18) -> 660650.77
B15: Development and pre construciton costs | F15: Land/lease | G15: 0 | J15: ITC
B16: Install cost/W | C16: 1.65 | F16: Municipal Incentives | G16: 0
B17: Construction costs | C17: =C16*C5*1000 -> 2722500 | F17: property taxes | G17: 0 | J17: ITC eligible (y/n) | K17: y
B18: Municipal fees | C18: 75000 | F18: insurance | G18: 0 | J18: ITC rate | K18: 0.3
B19: Interconnection | C19: 460000 | F19: O and M rate ($/kW) | G19: 12 | J19: Eligible Costs assumptions | K19: 0.95
B20: Development Fees | C20: 0 | F20: O and M cost | G20: =G19*C5 -> 19800 | J20: Eligible Costs | K20: =K19*C17 -> 2586375
B21: Total project Cost | C21: =SUM(C15:C20) -> 3257501.6 | F21: Variable Operating costs ($/kw) | G21: 0.8 | J21: Non Eligible costs | K21: =C23-K20 -> 680277.09
F22: Variable Operating costs ($) | G22: =G21*C5 -> 1320 | J22: Potential ITC Rebate | K22: =K20*K18 -> 775912.5
B23: All in Costs | C23: =C21+K10 -> 3266652.1 | F23: Total Opperations cost yr 1 | G23: =G20+G18+G17+G15+G22+G16 -> 21120 | J23: HQ ITC Clawback Rate | K23: 0
B24: Project cost ($/W) | C24: =(C21/C5)/1000 -> 1.9742434 | F24: Inflation | G24: 0.02 | J24: HQ ITC Clawback amount | K24: =K22*K23 -> 0
J25: Effective ITC Rebate to Project | K25: =K22-K24 -> 775912.5
F26: Major repairs 1 (yr) | G26: 0
F29: equipment reserve assumption $/W | G29: 0
F30: Equipment reserve requirements ($) | G30: =C5*G29*1000 -> 0 | J30: Pretax IRR | K30: =CashFlow!B26 -> 0.10085793

Sheet CashFlow
A3: Year | C3: 0 | D3: 1 | E3: 2 | F3: 3 | G3: 4 | H3: 5 | I3: 6 | J3: 7 | K3: 8 | L3: 9 | M3: 10 | N3: 11 | O3: 12 | P3: 13 | Q3: 14 | R3: 15 | S3: 16 | T3: 17 | U3: 18 | V3: 19 | W3: 20 | X3: 21 | Y3: 22 | Z3: 23 | AA3: 24 | AB3: 25 | AC3: 26 | AD3: 27 | AE3: 28 | AF3: 29 | AG3: 30
A4: Production | D4: =IF(D3<='Assumptions '!$C$11,('Assumptions '!$C$7/(1+(('Assumptions '!$C$9/100)*CashFlow!B3))*'Assumptions '!$C$5)*(1-('Assumptions '!$C$10)/100),0) -> 1888012.5 | E4: =IF(E3<='Assumptions '!$C$11,('Assumptions '!$C$7/(1+(('Assumptions '!$C$9/100)*CashFlow!C3))*'Assumptions '!$C$5)*(1-('Assumptions '!$C$10)/100),0) -> 1888012.5 | F4: =IF(F3<='Assumptions '!$C$11,('Assumptions '!$C$7/(1+(('Assumptions '!$C$9/100)*CashFlow!D3))*'Assumptions '!$C$5)*(1-('Assumptions '!$C$10)/100),0) -> 1878619.4 | G4: =IF(G3<='Assumptions '!$C$11,('Assumptions '!$C$7/(1+(('Assumptions '!$C$9/100)*CashFlow!E3))*'Assumptions '!$C$5)*(1-('Assumptions '!$C$10)/100),0) -> 1869319.3 | H4: =IF(H3<='Assumptions '!$C$11,('Assumptions '!$C$7/(1+(('Assumptions '!$C$9/100)*CashFlow!F3))*'Assumptions '!$C$5)*(1-('Assumptions '!$C$10)/100),0) -> 1860110.8 | I4: =IF(I3<='Assumptions '!$C$11,('Assumptions '!$C$7/(1+(('Assumptions '!$C$9/100)*CashFlow!G3))*'Assumptions '!$C$5)*(1-('Assumptions '!$C$10)/100),0) -> 1850992.6 | J4: =IF(J3<='Assumptions '!$C$11,('Assumptions '!$C$7/(1+(('Assumptions '!$C$9/100)*CashFlow!H3))*'Assumptions '!$C$5)*(1-('Assumptions '!$C$10)/100),0) -> 1841963.4 | K4: =IF(K3<='Assumptions '!$C$11,('Assumptions '!$C$7/(1+(('Assumptions '!$C$9/100)*CashFlow!I3))*'Assumptions '!$C$5)*(1-('Assumptions '!$C$10)/100),0) -> 1833021.8 | ... AB4: =IF(AB3<='Assumptions '!$C$11,('Assumptions '!$C$7/(1+(('Assumptions '!$C$9/100)*CashFlow!Z3))*'Assumptions '!$C$5)*(1-('Assumptions '!$C$10)/100),0) -> 1693284.8 | AC4: =IF(AC3<='Assumptions '!$C$11,('Assumptions '!$C$7/(1+(('Assumptions '!$C$9/100)*CashFlow!AB3))*'Assumptions '!$C$5)*'Assumptions '!$C$10,0) -> 0 | AD4: =IF(AD3<='Assumptions '!$C$11,('Assumptions '!$C$7/(1+(('Assumptions '!$C$9/100)*CashFlow!AC3))*'Assumptions '!$C$5)*'Assumptions '!$C$10,0) -> 0 | AE4: =IF(AE3<='Assumptions '!$C$11,('Assumptions '!$C$7/(1+(('Assumptions '!$C$9/100)*CashFlow!AD3))*'Assumptions '!$C$5)*'Assumptions '!$C$10,0) -> 0 | AF4: =IF(AF3<='Assumptions '!$C$11,('Assumptions '!$C$7/(1+(('Assumptions '!$C$9/100)*CashFlow!AE3))*'Assumptions '!$C$5)*'Assumptions '!$C$10,0) -> 0 | AG4: =IF(AG3<='Assumptions '!$C$11,('Assumptions '!$C$7/(1+(('Assumptions '!$C$9/100)*CashFlow!AF3))*'Assumptions '!$C$5)*'Assumptions '!$C$10,0) -> 0
A6: Capital expenditure | C6: =-IF('Assumptions '!K4="YES",('Assumptions '!C23-'Assumptions '!K6),'Assumptions '!C23) -> -1436563.3
A7: effective PPA rate | D7: ='Assumptions '!G5 -> 0.11 | E7: =D7+(D7*'Assumptions '!$G$6) -> 0.1122 | F7: =E7+(E7*'Assumptions '!$G$6) -> 0.114444 | G7: =F7+(F7*'Assumptions '!$G$6) -> 0.11673288 | H7: =G7+(G7*'Assumptions '!$G$6) -> 0.11906754 | I7: =H7+(H7*'Assumptions '!$G$6) -> 0.12144889 | J7: =I7+(I7*'Assumptions '!$G$6) -> 0.12387787 | K7: =J7+(J7*'Assumptions '!$G$6) -> 0.12635542 | L7: =K7+(K7*'Assumptions '!$G$6) -> 0.12888253 | ... AB7: =AA7+(AA7*'Assumptions '!$G$6) -> 0.1769281
A8: Revenue | C8: ='Assumptions '!K25 -> 775912.5 | D8: =IF(D3<='Assumptions '!$G$7,CashFlow!D4*CashFlow!D7,D4*CashFlow!$J$13) -> 207681.38 | E8: =IF(E3<='Assumptions '!$G$7,CashFlow!E4*CashFlow!E7,E4*CashFlow!$J$13) -> 211835 | F8: =IF(F3<='Assumptions '!$G$7,CashFlow!F4*CashFlow!F7,F4*CashFlow!$J$13) -> 214996.72 | G8: =IF(G3<='Assumptions '!$G$7,CashFlow!G4*CashFlow!G7,G4*CashFlow!$J$13) -> 218211.03 | H8: =IF(H3<='Assumptions '!$G$7,CashFlow!H4*CashFlow!H7,H4*CashFlow!$J$13) -> 221478.82 | I8: =IF(I3<='Assumptions '!$G$7,CashFlow!I4*CashFlow!I7,I4*CashFlow!$J$13) -> 224801 | J8: =IF(J3<='Assumptions '!$G$7,CashFlow!J4*CashFlow!J7,J4*CashFlow!$J$13) -> 228178.5 | K8: =IF(K3<='Assumptions '!$G$7,CashFlow!K4*CashFlow!K7,K4*CashFlow!$J$13) -> 231612.25 | ... AB8: =IF(AB3<='Assumptions '!$G$7,CashFlow!AB4*CashFlow!AB7,AB4*CashFlow!$J$13) -> 299589.65 | AC8: =IF(AC3<='Assumptions '!$G$7,CashFlow!AC4*'Assumptions '!$G$5,AC4*'Assumptions '!$G$8) -> 0 | AD8: =IF(AD3<='Assumptions '!$G$7,CashFlow!AD4*'Assumptions '!$G$5,AD4*'Assumptions '!$G$8) -> 0 | AE8: =IF(AE3<='Assumptions '!$G$7,CashFlow!AE4*'Assumptions '!$G$5,AE4*'Assumptions '!$G$8) -> 0 | AF8: =IF(AF3<='Assumptions '!$G$7,CashFlow!AF4*'Assumptions '!$G$5,AF4*'Assumptions '!$G$8) -> 0 | AG8: =IF(AG3<='Assumptions '!$G$7,CashFlow!AG4*'Assumptions '!$G$5,AG4*'Assumptions '!$G$8) -> 0
A11: Cash in | C11: =SUM(C8:C10) -> 775912.5 | D11: =SUM(D8:D10) -> 207681.38 | E11: =SUM(E8:E10) -> 211835 | F11: =SUM(F8:F10) -> 214996.72 | G11: =SUM(G8:G10) -> 218211.03 | H11: =SUM(H8:H10) -> 221478.82 | I11: =SUM(I8:I10) -> 224801 | J11: =SUM(J8:J10) -> 228178.5 | ... AG11: =SUM(AG8:AG10) -> 0
A13: Operating costs | B13: =SUM(D13:AG13) -> -676479.93 | D13: =-'Assumptions '!G23 -> -21120 | E13: =IF(E3<='Assumptions '!$C$11,CashFlow!D13*(1+'Assumptions '!$G$24),0) -> -21542.4 | F13: =IF(F3<='Assumptions '!$C$11,CashFlow!E13*(1+'Assumptions '!$G$24),0) -> -21973.248 | G13: =IF(G3<='Assumptions '!$C$11,CashFlow!F13*(1+'Assumptions '!$G$24),0) -> -22412.713 | H13: =IF(H3<='Assumptions '!$C$11,CashFlow!G13*(1+'Assumptions '!$G$24),0) -> -22860.967 | I13: =IF(I3<='Assumptions '!$C$11,CashFlow!H13*(1+'Assumptions '!$G$24),0) -> -23318.187 | J13: =IF(J3<='Assumptions '!$C$11,CashFlow!I13*(1+'Assumptions '!$G$24),0) -> -23784.55 | K13: =IF(K3<='Assumptions '!$C$11,CashFlow!J13*(1+'Assumptions '!$G$24),0) -> -24260.241 | L13: =IF(L3<='Assumptions '!$C$11,CashFlow!K13*(1+'Assumptions '!$G$24),0) -> -24745.446 | ... AG13: =IF(AG3<='Assumptions '!$C$11,CashFlow!AF13*(1+'Assumptions '!$G$24),0) -> 0
A15: EBITA | C15: =C11+C13 -> 775912.5 | D15: =D11+D13 -> 186561.38 | E15: =E11+E13 -> 190292.6 | F15: =F11+F13 -> 193023.47 | G15: =G11+G13 -> 195798.31 | H15: =H11+H13 -> 198617.85 | I15: =I11+I13 -> 201482.81 | J15: =J11+J13 -> 204393.95 | ... AG15: =AG11+AG13 -> 0
A17: Debt Service | B17: =SUM(D17:AG17) -> -2903139.5 | D17: =IF('Assumptions '!$K$4="YES",IF(D3<='Assumptions '!$K$7,PMT('Assumptions '!$K$8,'Assumptions '!$K$7,'Assumptions '!$K$6,0,1),0),0) -> -145156.97 | E17: =IF('Assumptions '!$K$4="YES",IF(E3<='Assumptions '!$K$7,PMT('Assumptions '!$K$8,'Assumptions '!$K$7,'Assumptions '!$K$6,0,1),0),0) -> -145156.97 | F17: =IF('Assumptions '!$K$4="YES",IF(F3<='Assumptions '!$K$7,PMT('Assumptions '!$K$8,'Assumptions '!$K$7,'Assumptions '!$K$6,0,1),0),0) -> -145156.97 | G17: =IF('Assumptions '!$K$4="YES",IF(G3<='Assumptions '!$K$7,PMT('Assumptions '!$K$8,'Assumptions '!$K$7,'Assumptions '!$K$6,0,1),0),0) -> -145156.97 | H17: =IF('Assumptions '!$K$4="YES",IF(H3<='Assumptions '!$K$7,PMT('Assumptions '!$K$8,'Assumptions '!$K$7,'Assumptions '!$K$6,0,1),0),0) -> -145156.97 | I17: =IF('Assumptions '!$K$4="YES",IF(I3<='Assumptions '!$K$7,PMT('Assumptions '!$K$8,'Assumptions '!$K$7,'Assumptions '!$K$6,0,1),0),0) -> -145156.97 | J17: =IF('Assumptions '!$K$4="YES",IF(J3<='Assumptions '!$K$7,PMT('Assumptions '!$K$8,'Assumptions '!$K$7,'Assumptions '!$K$6,0,1),0),0) -> -145156.97 | K17: =IF('Assumptions '!$K$4="YES",IF(K3<='Assumptions '!$K$7,PMT('Assumptions '!$K$8,'Assumptions '!$K$7,'Assumptions '!$K$6,0,1),0),0) -> -145156.97 | ... AG17: =IF('Assumptions '!$K$4="YES",IF(AG3<='Assumptions '!$K$7,PMT('Assumptions '!$K$8,'Assumptions '!$K$7,'Assumptions '!$K$6,0,1),0),0) -> 0
A18: DSCR | D18: =IF('Assumptions '!$K$4="YES",IF(D3<='Assumptions '!$K$7,ABS(D15/D17),0),0) -> 1.2852388 | E18: =IF('Assumptions '!$K$4="YES",IF(E3<='Assumptions '!$K$7,ABS(E15/E17),0),0) -> 1.3109436 | F18: =IF('Assumptions '!$K$4="YES",IF(F3<='Assumptions '!$K$7,ABS(F15/F17),0),0) -> 1.3297568 | G18: =IF('Assumptions '!$K$4="YES",IF(G3<='Assumptions '!$K$7,ABS(G15/G17),0),0) -> 1.3488729 | H18: =IF('Assumptions '!$K$4="YES",IF(H3<='Assumptions '!$K$7,ABS(H15/H17),0),0) -> 1.368297 | I18: =IF('Assumptions '!$K$4="YES",IF(I3<='Assumptions '!$K$7,ABS(I15/I17),0),0) -> 1.388034 | J18: =IF('Assumptions '!$K$4="YES",IF(J3<='Assumptions '!$K$7,ABS(J15/J17),0),0) -> 1.4080891 | K18: =IF('Assumptions '!$K$4="YES",IF(K3<='Assumptions '!$K$7,ABS(K15/K17),0),0) -> 1.4284674 | ... AG18: =IF('Assumptions '!$K$4="YES",IF(AG3<='Assumptions '!$K$7,ABS(AG15/AG17),0),0) -> 0
A19: Pass/fail | D19: =IF('Assumptions '!$K$4="YES",IF(D18<'Assumptions '!$K$11,"Fail","Pass"),0) -> Pass | E19: =IF('Assumptions '!$K$4="YES",IF(E18<'Assumptions '!$K$11,"Fail","Pass"),0) -> Pass | F19: =IF('Assumptions '!$K$4="YES",IF(F18<'Assumptions '!$K$11,"Fail","Pass"),0) -> Pass | G19: =IF('Assumptions '!$K$4="YES",IF(G18<'Assumptions '!$K$11,"Fail","Pass"),0) -> Pass | H19: =IF('Assumptions '!$K$4="YES",IF(H18<'Assumptions '!$K$11,"Fail","Pass"),0) -> Pass | I19: =IF('Assumptions '!$K$4="YES",IF(I18<'Assumptions '!$K$11,"Fail","Pass"),0) -> Pass | J19: =IF('Assumptions '!$K$4="YES",IF(J18<'Assumptions '!$K$11,"Fail","Pass"),0) -> Pass | K19: =IF('Assumptions '!$K$4="YES",IF(K18<'Assumptions '!$K$11,"Fail","Pass"),0) -> Pass | ... AG19: =IF('Assumptions '!$K$4="YES",IF(AG18<'Assumptions '!$K$11,"Fail","Pass"),0) -> Fail
A21: Maintenance reserve | D21: =IF(D3<'Assumptions '!$G$26,'Assumptions '!$G$30/('Assumptions '!$G$26-1),IF(CashFlow!D3='Assumptions '!$G$26,0,IF(CashFlow!D3<'Assumptions '!$G$27,'Assumptions '!$G$30/('Assumptions '!$G$27-'Assumptions '!$G$26-1),0))) -> 0 | E21: =IF(E3<'Assumptions '!$G$26,'Assumptions '!$G$30/('Assumptions '!$G$26-1),IF(CashFlow!E3='Assumptions '!$G$26,0,IF(CashFlow!E3<'Assumptions '!$G$27,'Assumptions '!$G$30/('Assumptions '!$G$27-'Assumptions '!$G$26-1),0))) -> 0 | F21: =IF(F3<'Assumptions '!$G$26,'Assumptions '!$G$30/('Assumptions '!$G$26-1),IF(CashFlow!F3='Assumptions '!$G$26,0,IF(CashFlow!F3<'Assumptions '!$G$27,'Assumptions '!$G$30/('Assumptions '!$G$27-'Assumptions '!$G$26-1),0))) -> 0 | G21: =IF(G3<'Assumptions '!$G$26,'Assumptions '!$G$30/('Assumptions '!$G$26-1),IF(CashFlow!G3='Assumptions '!$G$26,0,IF(CashFlow!G3<'Assumptions '!$G$27,'Assumptions '!$G$30/('Assumptions '!$G$27-'Assumptions '!$G$26-1),0))) -> 0 | H21: =IF(H3<'Assumptions '!$G$26,'Assumptions '!$G$30/('Assumptions '!$G$26-1),IF(CashFlow!H3='Assumptions '!$G$26,0,IF(CashFlow!H3<'Assumptions '!$G$27,'Assumptions '!$G$30/('Assumptions '!$G$27-'Assumptions '!$G$26-1),0))) -> 0 | I21: =IF(I3<'Assumptions '!$G$26,'Assumptions '!$G$30/('Assumptions '!$G$26-1),IF(CashFlow!I3='Assumptions '!$G$26,0,IF(CashFlow!I3<'Assumptions '!$G$27,'Assumptions '!$G$30/('Assumptions '!$G$27-'Assumptions '!$G$26-1),0))) -> 0 | J21: =IF(J3<'Assumptions '!$G$26,'Assumptions '!$G$30/('Assumptions '!$G$26-1),IF(CashFlow!J3='Assumptions '!$G$26,0,IF(CashFlow!J3<'Assumptions '!$G$27,'Assumptions '!$G$30/('Assumptions '!$G$27-'Assumptions '!$G$26-1),0))) -> 0 | K21: =IF(K3<'Assumptions '!$G$26,'Assumptions '!$G$30/('Assumptions '!$G$26-1),IF(CashFlow!K3='Assumptions '!$G$26,0,IF(CashFlow!K3<'Assumptions '!$G$27,'Assumptions '!$G$30/('Assumptions '!$G$27-'Assumptions '!$G$26-1),0))) -> 0 | ... AG21: =IF(AG3<'Assumptions '!$G$26,'Assumptions '!$G$30/('Assumptions '!$G$26-1),IF(CashFlow!AG3='Assumptions '!$G$26,0,IF(CashFlow!AG3<'Assumptions '!$G$27,'Assumptions '!$G$30/('Assumptions '!$G$27-'Assumptions '!$G$26-1),0))) -> 0
A23: Maintenance reserve Balance | B23: 0 | D23: =IF(D3='Assumptions '!$G$26,0,IF(CashFlow!D3='Assumptions '!$G$27,0,B23+D21)) -> 0 | E23: =IF(E3='Assumptions '!$G$26,0,IF(CashFlow!E3='Assumptions '!$G$27,0,D23+E21)) -> 0 | F23: =IF(F3='Assumptions '!$G$26,0,IF(CashFlow!F3='Assumptions '!$G$27,0,E23+F21)) -> 0 | G23: =IF(G3='Assumptions '!$G$26,0,IF(CashFlow!G3='Assumptions '!$G$27,0,F23+G21)) -> 0 | H23: =IF(H3='Assumptions '!$G$26,0,IF(CashFlow!H3='Assumptions '!$G$27,0,G23+H21)) -> 0 | I23: =IF(I3='Assumptions '!$G$26,0,IF(CashFlow!I3='Assumptions '!$G$27,0,H23+I21)) -> 0 | J23: =IF(J3='Assumptions '!$G$26,0,IF(CashFlow!J3='Assumptions '!$G$27,0,I23+J21)) -> 0 | K23: =IF(K3='Assumptions '!$G$26,0,IF(CashFlow!K3='Assumptions '!$G$27,0,J23+K21)) -> 0 | L23: =IF(L3='Assumptions '!$G$26,0,IF(CashFlow!L3='Assumptions '!$G$27,0,K23+L21)) -> 0 | ... AG23: =IF(AG3='Assumptions '!$G$26,0,IF(CashFlow!AG3='Assumptions '!$G$27,0,AF23+AG21)) -> 0
A25: Pre Tax Cashflows | C25: =C6+C15+C17-C21 -> -660650.77 | D25: =D6+D15+D17-D21 -> 41404.402 | E25: =E15+E17-E21 -> 45135.63 | F25: =F15+F17-F21 -> 47866.498 | G25: =G15+G17-G21 -> 50641.341 | H25: =H15+H17-H21 -> 53460.877 | I25: =I15+I17-I21 -> 56325.84 | J25: =J15+J17-J21 -> 59236.974 | K25: =K15+K17-K21 -> 62195.037 | L25: =L15+L17-L21 -> 65200.8 | ... AG25: =AG15+AG17-AG21 -> 0
A26: Pretax IRR | B26: =IRR(C25:AK25) -> 0.10085793
